vira/__init__.py
vira/py.typed
vira/vira_add_parent.py
vira/vira_base.py
vira/vira_copy.py
vira/vira_deep_copy.py
vira/vira_error.py
vira/vira_issue.py
vira/vira_script_utils.py
vira/vira_vira.py
volvo_jira-0.1.3.dist-info/LICENSE
volvo_jira-0.1.3.dist-info/METADATA
volvo_jira-0.1.3.dist-info/WHEEL
volvo_jira-0.1.3.dist-info/entry_points.txt
volvo_jira-0.1.3.dist-info/top_level.txt
volvo_jira-0.1.3.dist-info/RECORD
